mal_api/__init__.py
mal_api/__main__.py
mal_api/auth.py
mal_api/client.py
mal_api/listener.py
mal_api/types__client.py
mal_api/userAnimeList.py
mal_api/userData.py
myanimelist_api-0.1.4.dist-info/METADATA
myanimelist_api-0.1.4.dist-info/WHEEL
myanimelist_api-0.1.4.dist-info/entry_points.txt
myanimelist_api-0.1.4.dist-info/top_level.txt
myanimelist_api-0.1.4.dist-info/RECORD
