Metadata-Version: 2.4
Name: myanimelist-api
Version: 0.1.4
Summary: My Anime List Api Client and Auth.
Home-page: https://github.com/PandeCode/MalApi
Author: PandeCode
Author-email: 47388214+PandeCode@users.noreply.github.com
License: MIT
Classifier: License :: OSI Approved :: MIT License
Classifier: Programming Language :: Python :: 3
Classifier: Programming Language :: Python :: 3.9
Requires-Dist: flask
Requires-Dist: requests
Dynamic: author
Dynamic: author-email
Dynamic: classifier
Dynamic: description
Dynamic: description-content-type
Dynamic: home-page
Dynamic: license
Dynamic: requires-dist
Dynamic: summary
